<?xml version="1.0" encoding="UTF-8"?>
<!DOCTYPE fontscolors PUBLIC "-//NetBeans//DTD Editor Fonts and Colors settings 1.1//EN" "http://www.netbeans.org/dtds/EditorFontsColors-1_1.dtd">
<fontscolors>
    <fontcolor name="mark-occurrences"/>
    <fontcolor default="comment" name="COMMENT_HTML">
        <font style="bold"/>
    </fontcolor>
    <fontcolor default="regexp" foreColor="ffcc99ff" name="mod-regexp"/>
    <fontcolor foreColor="white" name="mod-global"/>
    <fontcolor foreColor="ffff0099" name="mod-method">
        <font style="bold"/>
    </fontcolor>
    <fontcolor foreColor="ffff0099" name="mod-class">
        <font style="bold"/>
    </fontcolor>
</fontscolors>
